CtpPlus/__init__.py
CtpPlus/CTP/ApiConst.py
CtpPlus/CTP/ApiStruct.py
CtpPlus/CTP/FutureAccount.py
CtpPlus/CTP/MdApi.py
CtpPlus/CTP/MdApiBase.cp38-win_amd64.pyd
CtpPlus/CTP/QueryInstrumentHelper.py
CtpPlus/CTP/ReqAuthenticate.py
CtpPlus/CTP/TraderApi.py
CtpPlus/CTP/TraderApiBase.cp38-win_amd64.pyd
CtpPlus/CTP/__init__.py
CtpPlus/CTP/thostmduserapi_se.dll
CtpPlus/CTP/thosttraderapi_se.dll
CtpPlus/examples/get_bar.py
CtpPlus/examples/get_tick.py
CtpPlus/examples/macd_strategy.py
CtpPlus/examples/moving_average_strategy.py
CtpPlus/examples/profit_loss_manager.py
CtpPlus/examples/rolling_trade.py
CtpPlus/examples/show_traderApi.py
CtpPlus/examples/test_MdApi.py
CtpPlus/examples/test_TraderApi.py
CtpPlus/examples/test_to_csv.py
CtpPlus/examples/trade_demo.py
CtpPlus/ta/__init__.py
CtpPlus/ta/time_bar.py
CtpPlus/utils/__init__.py
CtpPlus/utils/base_field.py
CtpPlus/utils/check_service.py
ctpplus-6.7.11.dist-info/LICENSE
ctpplus-6.7.11.dist-info/METADATA
ctpplus-6.7.11.dist-info/WHEEL
ctpplus-6.7.11.dist-info/top_level.txt
ctpplus-6.7.11.dist-info/RECORD
