Metadata-Version: 2.1
Name: ctpplus
Version: 6.7.11
Summary: CTP官方API的封装的Python版。
Home-page: https://gitee.com/syealfalfa/CtpPlus-master
Author: jyl
Author-email: 1650806563@qq.com
License: UNKNOWN
Keywords: CTP程序化交易
Platform: Windows
Platform: Linux
Requires-Python: >=3.7
